click_logging/__init__.py
click_logging/core.py
click_logging/options.py
click_logging-1.0.1.dist-info/LICENSE
click_logging-1.0.1.dist-info/METADATA
click_logging-1.0.1.dist-info/WHEEL
click_logging-1.0.1.dist-info/top_level.txt
click_logging-1.0.1.dist-info/zip-safe
click_logging-1.0.1.dist-info/RECORD
